{
 "aggregate_function_based_on": "",
 "creation": "2025-12-18 14:21:34.833085",
 "currency": "",
 "docstatus": 0,
 "doctype": "Number Card",
 "document_type": "Work Order",
 "dynamic_filters_json": "[[\"Work Order\",\"company\",\"=\",\"frappe.defaults.get_user_default(\\\"Company\\\")\"]]",
 "filters_json": "[[\"Work Order\",\"docstatus\",\"=\",\"1\"],[\"Work Order\",\"status\",\"=\",\"Not Started\"]]",
 "function": "Count",
 "idx": 1,
 "is_public": 1,
 "is_standard": 1,
 "label": "Open Work Orders",
 "modified": "2025-12-18 21:38:05.877071",
 "modified_by": "Administrator",
 "module": "Manufacturing",
 "name": "Open Work Orders",
 "owner": "Administrator",
 "parent_document_type": "",
 "report_function": "Sum",
 "show_full_number": 0,
 "show_percentage_stats": 1,
 "stats_time_interval": "Daily",
 "type": "Document Type"
}
